Workbook
Name aporte: 'Invest ID'!$D$8
Name dividendo: 'Invest ID'!$D$15
Name patrimonio: 'Invest ID'!$D$14
Name Perfil_investimento: 'Invest ID'!$D$6
Name qtd_anos: 'Invest ID'!$D$12
Name rendimento_carteira: 'Invest ID'!$D$5
Name salario: 'Invest ID'!$D$4
Name sugestao_investimento: 'Invest ID'!$D$7
Name sugestao_investimento_porcent: 'Invest ID'!$C$37:$C$43
Name taxa_mensal: 'Invest ID'!$D$13

Sheet Invest ID
A1: #VALUE!
B3: Configurações de Perfil
B4: Qual o seu Salário?
B5: Rendimento Carteira?
B6: Qual o seu Perfil de Investimento? | D6: Moderado
B7: Nossa Sugestão de Investimento | D7: =VLOOKUP(Perfil_investimento,Tabela8[#All],2,FALSE)*salario -> 0
B8: Quanto Desejo Investir por Mês?
B10: Investimento Mensal
B11: Aporte Mensal | D11: =aporte -> 0
B12: Por Quantos Anos?
B13: Taxa de Rendimento Mensal?
B14: Patrimonio Acumulado? | D14: =FV(taxa_mensal,qtd_anos*12,aporte*-1) -> 0
B15: Dividendos Mensais? | D15: =patrimonio*rendimento_carteira -> 0
B17: Cenários | C17: Patrimonio Acumulado | D17: Dividendos
B18: Quanto em 2 Anos? | C18: =FV(taxa_mensal,VALUE(MID($B18,10,SEARCH(" ",$B18,11)-10))*12,aporte*-1) -> 0 | D18: =$C18*$D$5 -> 0
B19: Quanto em 5 Anos? | C19: =FV(taxa_mensal,VALUE(MID($B19,10,SEARCH(" ",$B19,11)-10))*12,aporte*-1) -> 0 | D19: =$C19*$D$5 -> 0
B20: Quanto em 10 Anos? | C20: =FV(taxa_mensal,VALUE(MID($B20,10,SEARCH(" ",$B20,11)-10))*12,aporte*-1) -> 0 | D20: =$C20*$D$5 -> 0
B21: Quanto em 20 Anos? | C21: =FV(taxa_mensal,VALUE(MID($B21,10,SEARCH(" ",$B21,11)-10))*12,aporte*-1) -> 0 | D21: =$C21*$D$5 -> 0
B22: Quanto em 30 Anos? | C22: =FV(taxa_mensal,VALUE(MID($B22,10,SEARCH(" ",$B22,11)-10))*12,aporte*-1) -> 0 | D22: =$C22*$D$5 -> 0
B24: Patrimônio Acumulado
B37: Tipo de FII | C37: Sugestão Investimento (%) | D37: Valores
B38: Papel | C38: =VLOOKUP($D$6&"-"&$B38,Planilha1!$A:$D,4,FALSE) -> 0.32 | D38: =aporte*$C38 -> 0
B39: Tijolo | C39: =VLOOKUP($D$6&"-"&$B39,Planilha1!$A:$D,4,FALSE) -> 0.35 | D39: =aporte*$C39 -> 0
B40: Híbrido | C40: =VLOOKUP($D$6&"-"&$B40,Planilha1!$A:$D,4,FALSE) -> 0.08 | D40: =aporte*$C40 -> 0
B41: FOFs | C41: =VLOOKUP($D$6&"-"&$B41,Planilha1!$A:$D,4,FALSE) -> 0.05 | D41: =aporte*$C41 -> 0
B42: Desenvolvimento | C42: =VLOOKUP($D$6&"-"&$B42,Planilha1!$A:$D,4,FALSE) -> 0.1 | D42: =aporte*$C42 -> 0
B43: Hotelaria | C43: =VLOOKUP($D$6&"-"&$B43,Planilha1!$A:$D,4,FALSE) -> 0.1 | D43: =aporte*$C43 -> 0
D44: =SUM(D38:D43) -> 0
B46: Sugestão de Distribuição dos FII

Sheet Planilha1
A1: Chave | B1: Perfil | C1: FII | D1: % | F1: Perfil | G1: Aporte | I1: 2
A2: =Tabela7[[#This Row],[Perfil]]&"-"&Tabela7[[#This Row],[FII]] -> Conservador-Papel | B2: Conservador | C2: Papel | D2: 0.3 | F2: Conservador | G2: 0.1 | I2: 5
A3: =Tabela7[[#This Row],[Perfil]]&"-"&Tabela7[[#This Row],[FII]] -> Conservador-Tijolo | B3: Conservador | C3: Tijolo | D3: 0.5 | F3: Moderado | G3: 0.2 | I3: 10
A4: =Tabela7[[#This Row],[Perfil]]&"-"&Tabela7[[#This Row],[FII]] -> Conservador-Híbrido | B4: Conservador | C4: Híbrido | D4: 0.1 | F4: Agressivo | G4: 0.3 | I4: 20
A5: =Tabela7[[#This Row],[Perfil]]&"-"&Tabela7[[#This Row],[FII]] -> Conservador-FOFs | B5: Conservador | C5: FOFs | D5: 0.1 | I5: 30
A6: =Tabela7[[#This Row],[Perfil]]&"-"&Tabela7[[#This Row],[FII]] -> Conservador-Desenvolvimento | B6: Conservador | C6: Desenvolvimento | D6: 0
A7: =Tabela7[[#This Row],[Perfil]]&"-"&Tabela7[[#This Row],[FII]] -> Conservador-Hotelaria | B7: Conservador | C7: Hotelaria | D7: 0
A8: =Tabela7[[#This Row],[Perfil]]&"-"&Tabela7[[#This Row],[FII]] -> Moderado-Papel | B8: Moderado | C8: Papel | D8: 0.32
A9: =Tabela7[[#This Row],[Perfil]]&"-"&Tabela7[[#This Row],[FII]] -> Moderado-Tijolo | B9: Moderado | C9: Tijolo | D9: 0.35
A10: =Tabela7[[#This Row],[Perfil]]&"-"&Tabela7[[#This Row],[FII]] -> Moderado-Híbrido | B10: Moderado | C10: Híbrido | D10: 0.08
A11: =Tabela7[[#This Row],[Perfil]]&"-"&Tabela7[[#This Row],[FII]] -> Moderado-FOFs | B11: Moderado | C11: FOFs | D11: 0.05
A12: =Tabela7[[#This Row],[Perfil]]&"-"&Tabela7[[#This Row],[FII]] -> Moderado-Desenvolvimento | B12: Moderado | C12: Desenvolvimento | D12: 0.1
A13: =Tabela7[[#This Row],[Perfil]]&"-"&Tabela7[[#This Row],[FII]] -> Moderado-Hotelaria | B13: Moderado | C13: Hotelaria | D13: 0.1
A14: =Tabela7[[#This Row],[Perfil]]&"-"&Tabela7[[#This Row],[FII]] -> Agressivo-Papel | B14: Agressivo | C14: Papel | D14: 0.5
A15: =Tabela7[[#This Row],[Perfil]]&"-"&Tabela7[[#This Row],[FII]] -> Agressivo-Tijolo | B15: Agressivo | C15: Tijolo | D15: 0.1
A16: =Tabela7[[#This Row],[Perfil]]&"-"&Tabela7[[#This Row],[FII]] -> Agressivo-Híbrido | B16: Agressivo | C16: Híbrido | D16: 0.05
A17: =Tabela7[[#This Row],[Perfil]]&"-"&Tabela7[[#This Row],[FII]] -> Agressivo-FOFs | B17: Agressivo | C17: FOFs | D17: 0.05
... A19: =Tabela7[[#This Row],[Perfil]]&"-"&Tabela7[[#This Row],[FII]] -> Agressivo-Hotelaria | B19: Agressivo | C19: Hotelaria | D19: 0.1
